plusminus/__init__.py
plusminus/plusminus.py
plusminus/examples/__init__.py
plusminus/examples/bottle_repl.py
plusminus/examples/business_arithmetic_parser.py
plusminus/examples/combinatorics_arithmetic_parser.py
plusminus/examples/console_repl.py
plusminus/examples/date_time_arithmetic_parser.py
plusminus/examples/dice_roll_parser.py
plusminus/examples/plusminus_demo.py
plusminus-0.8.1.dist-info/LICENSE
plusminus-0.8.1.dist-info/METADATA
plusminus-0.8.1.dist-info/WHEEL
plusminus-0.8.1.dist-info/top_level.txt
plusminus-0.8.1.dist-info/RECORD
