Metadata-Version: 2.1
Name: plusminus
Version: 0.8.1
Summary: +/- plusminus is a module that builds on the pyparsing infixNotation helper method to build easy-to-code and easy-to-use parsers for parsing and evaluating infix arithmetic expressions. plusminus's ArithmeticParser class includes separate parse and evaluate methods, handling operator precedence, override with parentheses, presence or absence of whitespace, built-in functions, and pre-defined and user-defined variables, functions, and operators.
Author-email: Paul McGuire <ptmcg+pm@gmail.com>
Project-URL: Homepage, https://github.com/pyparsing/plusminus
Project-URL: Issues, https://github.com/pyparsing/plusminus/issues
Project-URL: Documentation, https://github.com/pyparsing/plusminus/tree/master/doc
Classifier: License :: OSI Approved :: MIT License
Classifier: Development Status :: 4 - Beta
Classifier: Intended Audience :: Developers
Classifier: Operating System :: OS Independent
Classifier: Programming Language :: Python :: 3 :: Only
Classifier: Programming Language :: Python :: 3.6
Classifier: Programming Language :: Python :: 3.7
Classifier: Programming Language :: Python :: 3.8
Classifier: Programming Language :: Python :: 3.9
Classifier: Programming Language :: Python :: 3.10
Classifier: Programming Language :: Python :: 3.11
Classifier: Programming Language :: Python :: 3.12
Classifier: Programming Language :: Python :: 3.13
Classifier: Topic :: Software Development
Classifier: Topic :: Software Development :: Libraries :: Python Modules
Classifier: Topic :: Software Development :: User Interfaces
Classifier: Topic :: Text Processing
Classifier: Topic :: Text Processing :: General
Classifier: Topic :: Utilities
Requires-Python: >=3.7
License-File: LICENSE
Requires-Dist: pyparsing >=2.4.7
